pylitex/__init__.py
pylitex/base_info.py
pylitex/repl_interactor.py
pylitex/run.py
pylitex-0.2.1.dist-info/licenses/LICENSE
pylitex-0.2.1.dist-info/WHEEL
pylitex-0.2.1.dist-info/METADATA
pylitex-0.2.1.dist-info/RECORD
