Metadata-Version: 2.4
Name: pylitex
Version: 0.2.1
Summary: Python package for Litex core
Author-email: Hill Hong <scanfandprintf@icloud.com>
Requires-Python: >=3.9
License-Expression: MIT
Classifier: Programming Language :: Python :: 3
Classifier: Intended Audience :: Science/Research
Classifier: Topic :: Scientific/Engineering :: Mathematics
License-File: LICENSE
Requires-Dist: pexpect >= 4.8.0
Requires-Dist: requests >= 2.22.0
Project-URL: Homepage, https://github.com/litexlang/pylitex
Project-URL: Issues, https://github.com/litexlang/pylitex/issues
